pydantic_yaml/__init__.py
pydantic_yaml/dumper.py
pydantic_yaml/loader.py
pydantic_yaml/py.typed
pydantic_yaml/version.py
pydantic_yaml/_internals/__init__.py
pydantic_yaml/_internals/comments.py
pydantic_yaml/_internals/v1.py
pydantic_yaml/_internals/v2.py
pydantic_yaml/deprecated/types.py
pydantic_yaml/examples/__init__.py
pydantic_yaml/examples/base_models.py
pydantic_yaml/examples/common.py
pydantic_yaml/examples/base_models/a-1.1.yaml
pydantic_yaml/examples/base_models/a-1.2.yaml
pydantic_yaml/examples/base_models/a.yaml
pydantic_yaml/examples/base_models/b.yaml
pydantic_yaml/examples/base_models/has_enums.yaml
pydantic_yaml/examples/base_models/recursive.yaml
pydantic_yaml/examples/base_models/root_list_obj.yaml
pydantic_yaml/examples/base_models/root_list_str.yaml
pydantic_yaml/examples/base_models/uses_refs.yaml
pydantic_yaml/examples/commented/false/uses_refs.yaml
pydantic_yaml/examples/commented/fields/uses_refs.yaml
pydantic_yaml/examples/commented/models/uses_refs.yaml
pydantic_yaml/examples/commented/true/uses_refs.yaml
pydantic_yaml/examples/v1/__init__.py
pydantic_yaml/examples/v1/base_models.py
pydantic_yaml/examples/v2/__init__.py
pydantic_yaml/examples/v2/base_models.py
pydantic_yaml-1.6.0.dist-info/LICENSE
pydantic_yaml-1.6.0.dist-info/METADATA
pydantic_yaml-1.6.0.dist-info/WHEEL
pydantic_yaml-1.6.0.dist-info/top_level.txt
pydantic_yaml-1.6.0.dist-info/RECORD
