Metadata-Version: 2.1
Name: pydantic_yaml
Version: 1.6.0
Summary: YAML reading/writing for Pydantic models
Author-email: NowanIlfideme <git@nowan.dev>
License: MIT License
Project-URL: github, https://github.com/NowanIlfideme/pydantic-yaml
Project-URL: docs, https://pydantic-yaml.readthedocs.io/en/latest/
Project-URL: issues, https://github.com/NowanIlfideme/pydantic-yaml/issues
Project-URL: releasenotes, https://github.com/NowanIlfideme/pydantic-yaml/releases
Keywords: pydantic,yaml
Classifier: Programming Language :: Python :: 3 :: Only
Classifier: Development Status :: 5 - Production/Stable
Classifier: Intended Audience :: Developers
Classifier: License :: OSI Approved :: MIT License
Classifier: Topic :: Software Development
Classifier: Typing :: Typed
Classifier: Operating System :: OS Independent
Requires-Python: >=3.10
Provides-Extra: dev
Provides-Extra: docs
License-File: LICENSE
